src/App.py
src/Board.py
src/BoardValidator.py
src/BoardValidatorColumns.py
src/BoardValidatorDiagonals.py
src/BoardValidatorRows.py
src/Cell.py
src/Column.py
src/ConsoleRenderer.py
src/Game.py
src/Match.py
src/PlayerInput.py
src/__init__.py
src/constants.py
connect_4_cli-0.0.9.dist-info/LICENSE
connect_4_cli-0.0.9.dist-info/METADATA
connect_4_cli-0.0.9.dist-info/WHEEL
connect_4_cli-0.0.9.dist-info/entry_points.txt
connect_4_cli-0.0.9.dist-info/top_level.txt
connect_4_cli-0.0.9.dist-info/RECORD
