Metadata-Version: 2.1
Name: connect-4-cli
Version: 0.0.9
Summary: A CLI implementation of the classic connect 4 game
Home-page: https://github.com/gmso/connect-4-cli
Author: Germán Mené Santa Olaya
Author-email: german.mene@gmail.com
License: UNKNOWN
Platform: UNKNOWN
Classifier: Programming Language :: Python :: 3
Classifier: License :: OSI Approved :: MIT License
Classifier: Operating System :: OS Independent
Classifier: Environment :: Console
Classifier: Topic :: Games/Entertainment :: Board Games
Requires-Dist: rich
Requires-Dist: pynput
